beancount_pygments_lexer/__init__.py
beancount_pygments_lexer/_init_.py
beancount_pygments_lexer/lexer.py
beancount_pygments_lexer/util/__init__.py
beancount_pygments_lexer/util/version.py
beancount_pygments_lexer-0.1.2.dist-info/DESCRIPTION.rst
beancount_pygments_lexer-0.1.2.dist-info/METADATA
beancount_pygments_lexer-0.1.2.dist-info/RECORD
beancount_pygments_lexer-0.1.2.dist-info/WHEEL
beancount_pygments_lexer-0.1.2.dist-info/entry_points.txt
beancount_pygments_lexer-0.1.2.dist-info/metadata.json
beancount_pygments_lexer-0.1.2.dist-info/pbr.json
beancount_pygments_lexer-0.1.2.dist-info/top_level.txt
