Metadata-Version: 2.0
Name: beancount-pygments-lexer
Version: 0.1.2
Summary: A pygments-lexer for beancount-files.
Home-page: http://github.com/aumayr/beancount-pygments-lexer
Author: Dominik Aumayr
Author-email: dominik@aumayr.name
License: MIT
Platform: UNKNOWN
Classifier: Development Status :: 4 - Beta
Classifier: License :: OSI Approved :: MIT License
Classifier: Natural Language :: English
Classifier: Programming Language :: Python :: 3.3
Classifier: Programming Language :: Python :: 3.4
Classifier: Programming Language :: Python :: 3.5
Classifier: Programming Language :: Python :: 3 :: Only
Classifier: Topic :: Office/Business :: Financial :: Accounting
Requires-Dist: pygments (>=2.0.2)
